pims/__init__.py
pims/_version.py
pims/api.py
pims/base_frames.py
pims/bioformats.py
pims/cine.py
pims/display.py
pims/ffmpeg_reader.py
pims/frame.py
pims/image_reader.py
pims/image_sequence.py
pims/imageio_reader.py
pims/moviepy_reader.py
pims/norpix_reader.py
pims/process.py
pims/pyav_reader.py
pims/spe_stack.py
pims/tiff_stack.py
pims/tests/__init__.py
pims/tests/test_bioformats.py
pims/tests/test_cine.py
pims/tests/test_common.py
pims/tests/test_display.py
pims/tests/test_factories.py
pims/tests/test_frame.py
pims/tests/test_imseq.py
pims/tests/test_multidimensional.py
pims/tests/test_norpix.py
pims/tests/test_process.py
pims/utils/__init__.py
pims/utils/misc.py
pims/utils/sort.py
PIMS-0.6.0.dist-info/METADATA
PIMS-0.6.0.dist-info/WHEEL
PIMS-0.6.0.dist-info/top_level.txt
PIMS-0.6.0.dist-info/RECORD
