Metadata-Version: 2.1
Name: PIMS
Version: 0.6.0
Summary: Python Image Sequence
Home-page: https://github.com/soft-matter/pims
Author: PIMS Contributors
Author-email: dallan@pha.jhu.edu
License: BSD-3-clause
Platform: UNKNOWN
Classifier: Development Status :: 4 - Beta
Classifier: Programming Language :: Python :: 3
Classifier: Programming Language :: Python :: 3.7
Classifier: Programming Language :: Python :: 3.8
Classifier: Programming Language :: Python :: 3.9
Classifier: Programming Language :: Python :: 3.10
Requires-Python: >=3.7
Requires-Dist: imageio
Requires-Dist: numpy (>=1.19)
Requires-Dist: slicerator (>=0.9.8)
